Metadata-Version: 2.1
Name: twjqt
Version: 0.0.3
Summary: this is a qt process
Author: twj
Classifier: License :: OSI Approved :: MIT License
Requires-Python: >=3.6
License-File: LICENSE.txt
